Metadata-Version: 2.1
Name: TfIdfTransformer
Version: 0.1
Summary: A Tf-Idf transformer package
Home-page: https://github.com/Oytunkdnz/TfIdfTransformer
Author: Oytun
Author-email: oytunakdeniz@gmail.com
Classifier: Development Status :: 3 - Alpha
Classifier: Intended Audience :: Developers
Classifier: License :: OSI Approved :: MIT License
Classifier: Programming Language :: Python :: 3.6
Classifier: Programming Language :: Python :: 3.7
Classifier: Programming Language :: Python :: 3.8
